{
  "forumId" : "27",
  "threadId" : "31862",
  "title" : "hello from camberg",
  "originalUrl" : "https://ssvc.org.uk/phpbb/viewtopic.php?f=27&t=31862",
  "breadcrumbs" : [ {
    "url" : "./viewforum.php?f=41",
    "label" : "Events"
  }, {
    "url" : "./viewforum.php?f=27",
    "label" : "Bad Camberg"
  } ],
  "totalPosts" : 7,
  "pageNumber" : 1,
  "totalPages" : 1,
  "posts" : [ {
    "postId" : "232239",
    "author" : {
      "username" : "Tony Best",
      "userId" : "232239",
      "joined" : "Thu Mar 03, 2005 10:37 pm",
      "profileRank" : "SSVC Member",
      "location" : "Long Clawson. Leicestershire",
      "postCount" : "304",
      "avatarPath" : "http://i45.photobucket.com/albums/f71/007westy/178421.jpg"
    },
    "content" : "Just saying hello from all camberg/little britain.weather aweful; atmosphere great.",
    "lastEdited" : "Sat Jun 23, 2007 7:25 am"
  }, {
    "postId" : "232243",
    "author" : {
      "username" : "Reaction",
      "userId" : "232243",
      "joined" : "Thu Feb 26, 2004 1:56 pm",
      "profileRank" : "SSVC Member",
      "location" : "Mount St Ives, Nr Cambridge",
      "postCount" : "981",
      "avatarPath" : "http://img.photobucket.com/albums/v734/Toughplum/2busavatar.jpg"
    },
    "content" : "Pah, like we care. A horrible old town stuffed with knackered old cars... who would want to see that?!?!?!? \n<img class=\"smilies\" src=\"./images/smilies/icon_wink.gif\" alt=\":wink:\" title=\"Wink\"> \n<br> \n<br>Enjoy, and please be a happy snapper. \n<img class=\"smilies\" src=\"./images/smilies/icon_biggrin.gif\" alt=\":D\" title=\"Big Grin\">",
    "lastEdited" : "Sat Jun 23, 2007 7:34 am"
  }, {
    "postId" : "232252",
    "author" : {
      "username" : "John",
      "userId" : "232252",
      "joined" : "Tue Apr 15, 2003 6:32 pm",
      "profileRank" : "SSVC Committee Member",
      "location" : "Derby & In a field near you !",
      "postCount" : "1100",
      "avatarPath" : null
    },
    "content" : "It's raining here as well, The mud at Glastonbury is amusing........",
    "lastEdited" : "Sat Jun 23, 2007 7:55 am"
  }, {
    "postId" : "232270",
    "author" : {
      "username" : "bigbulli",
      "userId" : "232270",
      "joined" : "Thu Apr 17, 2003 8:24 am",
      "profileRank" : "SSVC Member",
      "location" : "Barnstaple, NORTH DEVON",
      "postCount" : "2809",
      "avatarPath" : "./download/file.php%3Favatar=22_1364739473.jpg"
    },
    "content" : "Dont forget to take lots of pictures for the people who couldn't make it.....or who had their flights with BA cancelled.....",
    "lastEdited" : "Sat Jun 23, 2007 9:39 am"
  }, {
    "postId" : "232281",
    "author" : {
      "username" : "Bergy",
      "userId" : "232281",
      "joined" : "Fri May 30, 2003 8:37 am",
      "profileRank" : "Registered user",
      "location" : "Dorset",
      "postCount" : "3854",
      "avatarPath" : "./download/file.php%3Favatar=294_1256210293.jpg"
    },
    "content" : "Hiya Tony !! hope you are all having a great time \n<img class=\"smilies\" src=\"./images/smilies/icon_biggrin.gif\" alt=\":D\" title=\"Big Grin\"> \n<br> \n<br>take lots of pics please \n<img class=\"smilies\" src=\"./images/smilies/icon_biggrin.gif\" alt=\":D\" title=\"Big Grin\">",
    "lastEdited" : "Sat Jun 23, 2007 11:38 am"
  }, {
    "postId" : "232300",
    "author" : {
      "username" : "vwJim",
      "userId" : "232300",
      "joined" : "Thu Apr 24, 2003 6:05 pm",
      "profileRank" : "Founder BWA Member",
      "location" : "under a bus in Hampshire...",
      "postCount" : "17429",
      "avatarPath" : "./download/file.php%3Favatar=124_1300829071.jpg"
    },
    "content" : "Never been in a campsite with wifi before.... \n<br> \n<br>There's some really cool stuff here as usual.... \n<img class=\"smilies\" src=\"./images/smilies/icon_biggrin.gif\" alt=\":D\" title=\"Big Grin\">",
    "lastEdited" : "Sat Jun 23, 2007 3:09 pm"
  }, {
    "postId" : "232756",
    "author" : {
      "username" : "Byron Bamboo",
      "userId" : "232756",
      "joined" : "Thu Apr 17, 2003 12:41 pm",
      "profileRank" : "SSVC Member",
      "location" : "Hampshire",
      "postCount" : "6824",
      "avatarPath" : "./download/file.php%3Favatar=38_1338322337.jpg"
    },
    "content" : "If i'd have known there was Wi-fi, we could have all had our SSVC fix.. while we were away... \n<br> \n<br>But then we were having to much fun away to worry about that!! \n<img class=\"smilies\" src=\"./images/smilies/icon_biggrin.gif\" alt=\":D\" title=\"Big Grin\"> \n<img class=\"smilies\" src=\"./images/smilies/icon_wink.gif\" alt=\":wink:\" title=\"Wink\">",
    "lastEdited" : "Tue Jun 26, 2007 8:20 am"
  } ]
}