{
  "forumId" : "47",
  "threadId" : "66774",
  "title" : "mauser bowl wreck",
  "originalUrl" : "https://ssvc.org.uk/phpbb/viewtopic.php?f=47&t=66774",
  "breadcrumbs" : [ ],
  "totalPosts" : 9,
  "pageNumber" : 1,
  "totalPages" : 1,
  "posts" : [ {
    "postId" : "515280",
    "author" : {
      "username" : "Unknown",
      "userId" : "515280",
      "joined" : "Tue Aug 07, 2007 3:39 pm",
      "profileRank" : "Registered user",
      "location" : "-",
      "postCount" : "1085",
      "avatarPath" : "http://www.bbc.co.uk/cult/ilove/years/1977/images/citizensmith173.jpg"
    },
    "content" : "some of you have already heard about this, but here it is for your info/amusement depending on your view...\n<br>\n<br>before..\n<br>\n<img src=\"http://i193.photobucket.com/albums/z6/wolfie53/24889_382355345395_656325395_496122.jpg\" class=\"postimage\" alt=\"Image\">\n<br>\n<br>after..\n<br>\n<img src=\"http://i193.photobucket.com/albums/z6/wolfie53/DSC_4175.jpg\" class=\"postimage\" alt=\"Image\">\n<br>\n<br>\n<!-- m -->\n<a class=\"postlink\" href=\"http://www.thesamba.com/vw/forum/viewtopic.php?t=418053\">http://www.thesamba.com/vw/forum/viewtopic.php?t=418053</a>\n<!-- m -->",
    "lastEdited" : "Wed Jun 09, 2010 12:08 am"
  }, {
    "postId" : "515292",
    "author" : {
      "username" : "snowman",
      "userId" : "515292",
      "joined" : "Sun Nov 30, 2003 7:41 pm",
      "profileRank" : "SSVC Member",
      "location" : "-",
      "postCount" : "1958",
      "avatarPath" : null
    },
    "content" : "Man you must be gutted , \n<img class=\"smilies\" src=\"./images/smilies/icon_sad.gif\" alt=\":(\" title=\"Sad\"> \n<br>please dont tell us you drove over it?",
    "lastEdited" : "Wed Jun 09, 2010 6:36 am"
  }, {
    "postId" : "515310",
    "author" : {
      "username" : "nick",
      "userId" : "515310",
      "joined" : "Sat Apr 26, 2003 2:32 am",
      "profileRank" : "SSVC Member",
      "location" : "hairy ford",
      "postCount" : "4803",
      "avatarPath" : null
    },
    "content" : "<img class=\"smilies\" src=\"./images/smilies/icon_eek.gif\" alt=\"8O\" title=\"eek\"> \n<img class=\"smilies\" src=\"./images/smilies/icon_eek.gif\" alt=\"8O\" title=\"eek\"> \n<img class=\"smilies\" src=\"./images/smilies/icon_eek.gif\" alt=\"8O\" title=\"eek\"> \n<img class=\"smilies\" src=\"./images/smilies/icon_eek.gif\" alt=\"8O\" title=\"eek\"> \n<img class=\"smilies\" src=\"./images/smilies/icon_eek.gif\" alt=\"8O\" title=\"eek\"> \n<img class=\"smilies\" src=\"./images/smilies/icon_exclaim.gif\" alt=\":!:\" title=\"Exclaim\"> \n<img class=\"smilies\" src=\"./images/smilies/icon_exclaim.gif\" alt=\":!:\" title=\"Exclaim\"> \n<img class=\"smilies\" src=\"./images/smilies/icon_exclaim.gif\" alt=\":!:\" title=\"Exclaim\"> \n<br>\n<br>I would have gone nucking futs!!!!!!!!!!!!!!!!!!!!!!!!!!!!!!!",
    "lastEdited" : "Wed Jun 09, 2010 7:49 am"
  }, {
    "postId" : "515341",
    "author" : {
      "username" : "surreysplit",
      "userId" : "515341",
      "joined" : "Tue Sep 11, 2007 6:41 am",
      "profileRank" : "SSVC Member",
      "location" : "Surrey....ish",
      "postCount" : "5610",
      "avatarPath" : null
    },
    "content" : "F**K me Steve , thats well out of order , more then gutted id imagine \n<img class=\"smilies\" src=\"./images/smilies/icon_sad.gif\" alt=\":(\" title=\"Sad\"> \n<img class=\"smilies\" src=\"./images/smilies/icon_sad.gif\" alt=\":(\" title=\"Sad\">",
    "lastEdited" : "Wed Jun 09, 2010 10:04 am"
  }, {
    "postId" : "515343",
    "author" : {
      "username" : "Unknown",
      "userId" : "515343",
      "joined" : "Tue Aug 07, 2007 3:39 pm",
      "profileRank" : "Registered user",
      "location" : "-",
      "postCount" : "1085",
      "avatarPath" : "http://www.bbc.co.uk/cult/ilove/years/1977/images/citizensmith173.jpg"
    },
    "content" : "<blockquote>\n <div>\n  <cite>nick wrote:</cite>8O \n  <img class=\"smilies\" src=\"./images/smilies/icon_eek.gif\" alt=\"8O\" title=\"eek\"> \n  <img class=\"smilies\" src=\"./images/smilies/icon_eek.gif\" alt=\"8O\" title=\"eek\"> \n  <img class=\"smilies\" src=\"./images/smilies/icon_eek.gif\" alt=\"8O\" title=\"eek\"> \n  <img class=\"smilies\" src=\"./images/smilies/icon_eek.gif\" alt=\"8O\" title=\"eek\"> \n  <img class=\"smilies\" src=\"./images/smilies/icon_exclaim.gif\" alt=\":!:\" title=\"Exclaim\"> \n  <img class=\"smilies\" src=\"./images/smilies/icon_exclaim.gif\" alt=\":!:\" title=\"Exclaim\"> \n  <img class=\"smilies\" src=\"./images/smilies/icon_exclaim.gif\" alt=\":!:\" title=\"Exclaim\"> \n  <br>\n  <br>I would have gone nucking futs!!!!!!!!!!!!!!!!!!!!!!!!!!!!!!!\n </div>\n</blockquote>\n<br>\n<br>yeah, I'm a little annoyed to say the least. \n<img class=\"smilies\" src=\"./images/smilies/icon_cry.gif\" alt=\":cry:\" title=\"Cry\"> real shame as it needn't have happened. I've spoken to the company in India and they assure me it was damaged on arrival becasue it wasn't packaged very well - it was just \"in a cardboard box with small packaging\". Should have been sent in a flight case or a wooden box at least considering how brittle they get. The nightmare I had to get it back was just insult to injury tbh. I still have had no word from Alex. Maybe he'll reply on here or the Samba - we'll see. I wasn't going to post it up but everyone else seemed to think it should go up as a warning to others.. so there you go.\n<br>\n<br>My next post will be be the usual.. 'mauser bowl wanted $$$' and I'll join the queue \n<img class=\"smilies\" src=\"./images/smilies/icon_lol.gif\" alt=\":lol:\" title=\"LOL\"> \n<br>\n<br>anyone got a tin of solvent weld? \n<img class=\"smilies\" src=\"./images/smilies/icon_biggrin.gif\" alt=\":D\" title=\"Big Grin\">",
    "lastEdited" : "Wed Jun 09, 2010 10:14 am"
  }, {
    "postId" : "515344",
    "author" : {
      "username" : "Unknown",
      "userId" : "515344",
      "joined" : "Tue Aug 07, 2007 3:39 pm",
      "profileRank" : "Registered user",
      "location" : "-",
      "postCount" : "1085",
      "avatarPath" : "http://www.bbc.co.uk/cult/ilove/years/1977/images/citizensmith173.jpg"
    },
    "content" : "<blockquote>\n <div>\n  <cite>surreysplit wrote:</cite>F**K me Steve , thats well out of order , more then gutted id imagine \n  <img class=\"smilies\" src=\"./images/smilies/icon_sad.gif\" alt=\":(\" title=\"Sad\"> \n  <img class=\"smilies\" src=\"./images/smilies/icon_sad.gif\" alt=\":(\" title=\"Sad\">\n </div>\n</blockquote>\n<br>Life goes on mate. I can pick up a new bowl for a couple of quid at the local hardware shop \n<img class=\"smilies\" src=\"./images/smilies/icon_rolleyes.gif\" alt=\":roll:\" title=\"Roll Eyes\"> \n<img class=\"smilies\" src=\"./images/smilies/icon_lol.gif\" alt=\":lol:\" title=\"LOL\">",
    "lastEdited" : "Wed Jun 09, 2010 10:17 am"
  }, {
    "postId" : "515345",
    "author" : {
      "username" : "Biglozzer",
      "userId" : "515345",
      "joined" : "Sat Jan 03, 2004 8:43 pm",
      "profileRank" : "SSVC Member",
      "location" : "Twickenham",
      "postCount" : "1772",
      "avatarPath" : "./download/file.php%3Favatar=644_1461920439.jpg"
    },
    "content" : "Steve you must be gutted mate. Hope you get compensated. On the bright side Homebase is 25% off this weekend. Loads of washing up bowls there! \n<img class=\"smilies\" src=\"./images/smilies/wink.gif\" alt=\";)\" title=\"Wink\"> \n<br>\n<br>Only joking - gutted for ya. \n<img class=\"smilies\" src=\"./images/smilies/icon_sad.gif\" alt=\":(\" title=\"Sad\">",
    "lastEdited" : "Wed Jun 09, 2010 10:19 am"
  }, {
    "postId" : "515998",
    "author" : {
      "username" : "fredo",
      "userId" : "515998",
      "joined" : "Fri Oct 28, 2005 4:46 pm",
      "profileRank" : "Registered user",
      "location" : "-",
      "postCount" : "204",
      "avatarPath" : "./download/file.php%3Favatar=1819_1338487173.jpg"
    },
    "content" : "very very bad news .. \n<img class=\"smilies\" src=\"./images/smilies/icon_eek.gif\" alt=\"8O\" title=\"eek\"> \n<img class=\"smilies\" src=\"./images/smilies/icon_evil.gif\" alt=\":evil:\" title=\"Evil\"> \n<br>Fred",
    "lastEdited" : "Fri Jun 11, 2010 7:39 pm"
  }, {
    "postId" : "784747",
    "author" : {
      "username" : "Arthur",
      "userId" : "784747",
      "joined" : "Fri Apr 25, 2003 7:20 pm",
      "profileRank" : "SSVC Member",
      "location" : "-",
      "postCount" : "304",
      "avatarPath" : "./download/file.php%3Favatar=136_1418414059.jpg"
    },
    "content" : "Really sorry to hear about your bowl.\n<br>\n<br>I sold one a little while ago out of my SO36.\n<br>\n<br>Arthur",
    "lastEdited" : "Fri May 16, 2014 8:23 am"
  } ]
}