{
  "forumId" : "5",
  "threadId" : "113937",
  "title" : "fold-down buddy seat wanted",
  "originalUrl" : "https://ssvc.org.uk/phpbb/viewtopic.php?f=5&t=113937",
  "breadcrumbs" : [ {
    "url" : "./viewforum.php?f=5&sid=ec2dca7b14077f3c5a44ae0efd4371cd",
    "label" : "Wanted"
  } ],
  "totalPosts" : 6,
  "pageNumber" : 1,
  "totalPages" : 1,
  "posts" : [ {
    "postId" : "859032",
    "author" : {
      "username" : "ernie",
      "userId" : "859032",
      "joined" : "Wed Sep 02, 2009 6:20 pm",
      "profileRank" : "Registered user",
      "location" : "-",
      "postCount" : "950",
      "avatarPath" : null
    },
    "content" : "Hi all,\n<br>\n<br>i am after a fold-down buddy seat, Rusty Lee stylie...\n<br>\n<br>\n<!-- m -->\n<a class=\"postlink\" href=\"https://www.google.co.uk/search?q=rusty+lee+buddy+seat&amp;biw=1309&amp;bih=705&amp;source=lnms&amp;tbm=isch&amp;sa=X&amp;ved=0ahUKEwjX0-r8zojKAhUGOBoKHchnBWMQ_AUIBygC#imgrc=nbV50t38MWIJ-M%3A\">https://www.google.co.uk/search?q=rusty ... 8MWIJ-M%3A</a>\n<!-- m -->\n<br>\n<br>Anyone got one?\n<br>\n<br>Thanks",
    "lastEdited" : "Fri Jan 01, 2016 12:31 pm"
  }, {
    "postId" : "860764",
    "author" : {
      "username" : "ernie",
      "userId" : "860764",
      "joined" : "Wed Sep 02, 2009 6:20 pm",
      "profileRank" : "Registered user",
      "location" : "-",
      "postCount" : "950",
      "avatarPath" : null
    },
    "content" : "still looking",
    "lastEdited" : "Sun Jan 17, 2016 6:17 pm"
  }, {
    "postId" : "861467",
    "author" : {
      "username" : "andy66split",
      "userId" : "861467",
      "joined" : "Sat Feb 13, 2010 6:26 pm",
      "profileRank" : "Registered user",
      "location" : "-",
      "postCount" : "728",
      "avatarPath" : null
    },
    "content" : "I have 3 flip seats Any good for you?",
    "lastEdited" : "Sun Jan 24, 2016 5:09 pm"
  }, {
    "postId" : "861474",
    "author" : {
      "username" : "ernie",
      "userId" : "861474",
      "joined" : "Wed Sep 02, 2009 6:20 pm",
      "profileRank" : "Registered user",
      "location" : "-",
      "postCount" : "950",
      "avatarPath" : null
    },
    "content" : "thanks for the offer, but I was looking for one as per the link above - the Rusty Lee one.",
    "lastEdited" : "Sun Jan 24, 2016 5:59 pm"
  }, {
    "postId" : "861825",
    "author" : {
      "username" : "Dai",
      "userId" : "861825",
      "joined" : "Tue Dec 20, 2005 4:34 pm",
      "profileRank" : "SSVC Member",
      "location" : "-",
      "postCount" : "3156",
      "avatarPath" : "http://i205.photobucket.com/albums/bb320/jaralu/annieplug.jpg"
    },
    "content" : "I think I have 2 OG bay ones in the shed, I'll take a look on the weekend.",
    "lastEdited" : "Wed Jan 27, 2016 1:36 pm"
  }, {
    "postId" : "861833",
    "author" : {
      "username" : "jayvanman",
      "userId" : "861833",
      "joined" : "Tue Aug 19, 2008 10:21 am",
      "profileRank" : "Registered user",
      "location" : "Bristol",
      "postCount" : "2793",
      "avatarPath" : "./download/file.php%3Favatar=28832_1285795027.jpg"
    },
    "content" : "£85 on Lee's website\n<br>\n<!-- m -->\n<a class=\"postlink\" href=\"http://www.vwrustylee.com/buddy-seats/\">http://www.vwrustylee.com/buddy-seats/</a>\n<!-- m -->",
    "lastEdited" : "Wed Jan 27, 2016 5:28 pm"
  } ]
}