{
  "forumId" : "51",
  "threadId" : "124861",
  "title" : "T2 Bay Westy Exchange",
  "originalUrl" : "https://ssvc.org.uk/phpbb/viewtopic.php?f=51&t=124861",
  "breadcrumbs" : [ {
    "url" : "./viewforum.php?f=51&sid=b6149ecb18e3f6d9d2f5b0077eb3cf79",
    "label" : "Buses For Sale"
  } ],
  "totalPosts" : 1,
  "pageNumber" : 1,
  "totalPages" : 1,
  "posts" : [ {
    "postId" : "930739",
    "author" : {
      "username" : "Jens53",
      "userId" : "930739",
      "joined" : "Mon Feb 04, 2019 7:08 am",
      "profileRank" : "Registered user",
      "location" : "-",
      "postCount" : "6",
      "avatarPath" : null
    },
    "content" : "Hello,\n<br> would exchange my 72 Westy for a split.\n<br> The Westy is in good condition, has an adjustable front axle and a nice interior.\n<br> We are looking for a German T1 LHD in good condition. Valuation report of 30,000 euros made last year. Unfortunately, alternator problems at the moment. Little things are always to be done - it has been standing for 4 months. I lost my temper.\n<br> So if you want to exchange a good split, feel free to report! Old V5 copy available, cause it was Usa Import to Uk and than to Germany.\n<br> Pictures per PN or per Mail. I can´t upload here \n<img class=\"smilies\" src=\"./images/smilies/icon_sad.gif\" width=\"15\" height=\"15\" alt=\":(\" title=\"Sad\"> \n<br> Greetings, Jens",
    "lastEdited" : "Wed Jun 24, 2020 6:10 am"
  } ]
}