{
  "forumId" : "7",
  "threadId" : "76150",
  "title" : "Frontseat stolen! needs help Cumbria area 150‚Ç¨ reward!",
  "originalUrl" : "https://ssvc.org.uk/phpbb/viewtopic.php?f=7&t=76150",
  "breadcrumbs" : [ {
    "url" : "./viewforum.php?f=7&sid=e2578238b1b4bdb99451bf1f9dee29df",
    "label" : "Stolen"
  } ],
  "totalPosts" : 12,
  "pageNumber" : 1,
  "totalPages" : 1,
  "posts" : [ {
    "postId" : "588440",
    "author" : {
      "username" : "Sancho",
      "userId" : "588440",
      "joined" : "Sat Jan 14, 2006 12:39 pm",
      "profileRank" : "Registered user",
      "location" : "Mechelen (Belgium)",
      "postCount" : "236",
      "avatarPath" : null
    },
    "content" : "Hy,\n<br>\n<br>I have send frontseat to lynleigh for reupholstery.\n<br>\n<!-- l -->\n<a class=\"postlink-local\" href=\"http://www.ssvc.org.uk/phpbb/viewtopic.php?f=4&amp;t=71725\">viewtopic.php?f=4&amp;t=71725</a>\n<!-- l -->\n<br>For 1 month now I don't receive any contact from him.\n<br>Doesn't answers mail nor PB's.\n<br>Takes up the phone (sometimes) but then everything stays silent.\n<br>Doesn't responds to textmessages.\n<br>Can somebody from the distington area please take a look for me?\n<br>(I have the adres but offcourse will only give it by PM)\n<br>There might be something going on, but he also removed the first post of his tread, so it all is a bit to worrying...\n<br>It would be best if lynleigh finished the seat and I can get it back finished.\n<br>\n<br>Thxs for your help!\n<br>Tanguy",
    "lastEdited" : "Sat May 28, 2011 2:46 pm"
  }, {
    "postId" : "588788",
    "author" : {
      "username" : "Sancho",
      "userId" : "588788",
      "joined" : "Sat Jan 14, 2006 12:39 pm",
      "profileRank" : "Registered user",
      "location" : "Mechelen (Belgium)",
      "postCount" : "236",
      "avatarPath" : null
    },
    "content" : "nobody from that area \n<img class=\"smilies\" src=\"./images/smilies/icon_question.gif\" alt=\":?:\" title=\"Question\">",
    "lastEdited" : "Mon May 30, 2011 7:26 pm"
  }, {
    "postId" : "589116",
    "author" : {
      "username" : "Sancho",
      "userId" : "589116",
      "joined" : "Sat Jan 14, 2006 12:39 pm",
      "profileRank" : "Registered user",
      "location" : "Mechelen (Belgium)",
      "postCount" : "236",
      "avatarPath" : null
    },
    "content" : "reward waiting!",
    "lastEdited" : "Wed Jun 01, 2011 11:31 am"
  }, {
    "postId" : "589588",
    "author" : {
      "username" : "Sancho",
      "userId" : "589588",
      "joined" : "Sat Jan 14, 2006 12:39 pm",
      "profileRank" : "Registered user",
      "location" : "Mechelen (Belgium)",
      "postCount" : "236",
      "avatarPath" : null
    },
    "content" : "up for the weekend,\n<br>nobody wants to catch a thief? \n<img class=\"smilies\" src=\"./images/smilies/smile.gif\" alt=\":-)\" title=\"Smile\">\n<br>\n<br>2 adresses: 7, ESK AVENUE, Cumbria, Whitehaven CA28 8AW\n<br>\n<br>or: Humbugs\n<br>Unit 3\n<br>Barfs Rd\n<br>Distington\n<br>Cumbria\n<br>CA145TG",
    "lastEdited" : "Fri Jun 03, 2011 11:23 am"
  }, {
    "postId" : "590358",
    "author" : {
      "username" : "Sancho",
      "userId" : "590358",
      "joined" : "Sat Jan 14, 2006 12:39 pm",
      "profileRank" : "Registered user",
      "location" : "Mechelen (Belgium)",
      "postCount" : "236",
      "avatarPath" : null
    },
    "content" : "common guys,\n<br>really need help!\n<br>150€ reward if you can recover my seat!",
    "lastEdited" : "Wed Jun 08, 2011 10:27 am"
  }, {
    "postId" : "590359",
    "author" : {
      "username" : "vwJim",
      "userId" : "590359",
      "joined" : "Thu Apr 24, 2003 6:05 pm",
      "profileRank" : "Founder BWA Member",
      "location" : "under a bus in Hampshire...",
      "postCount" : "17997",
      "avatarPath" : "./download/file.php%3Favatar=124_1300829071.jpg"
    },
    "content" : "No one else live up that way?",
    "lastEdited" : "Wed Jun 08, 2011 10:30 am"
  }, {
    "postId" : "590444",
    "author" : {
      "username" : "richierich37",
      "userId" : "590444",
      "joined" : "Sat Jul 12, 2008 7:10 am",
      "profileRank" : "SSVC Member",
      "location" : "-",
      "postCount" : "1160",
      "avatarPath" : null
    },
    "content" : "would the police be interested in this? \n<img class=\"smilies\" src=\"./images/smilies/icon_confused.gif\" alt=\":?\" title=\"Confused\">",
    "lastEdited" : "Wed Jun 08, 2011 5:42 pm"
  }, {
    "postId" : "590464",
    "author" : {
      "username" : "Sancho",
      "userId" : "590464",
      "joined" : "Sat Jan 14, 2006 12:39 pm",
      "profileRank" : "Registered user",
      "location" : "Mechelen (Belgium)",
      "postCount" : "236",
      "avatarPath" : null
    },
    "content" : "I have mailed the cumbria police, and they can't be bothered \n<img class=\"smilies\" src=\"./images/smilies/icon_evil.gif\" alt=\":evil:\" title=\"Evil\">",
    "lastEdited" : "Wed Jun 08, 2011 6:36 pm"
  }, {
    "postId" : "590475",
    "author" : {
      "username" : "PJGoose69",
      "userId" : "590475",
      "joined" : "Sun Oct 05, 2008 9:05 pm",
      "profileRank" : "Registered user",
      "location" : "Hilton, Derbyshire",
      "postCount" : "698",
      "avatarPath" : "http://i168.photobucket.com/albums/u167/PJGoose69_album/Splitty/stanfordhall022-1.jpg"
    },
    "content" : "Perhaps try on VZi? Broaden your options to find someone local...bound to be a fellow VW owner local that is willing to help you!!\n<br>Good luck.",
    "lastEdited" : "Wed Jun 08, 2011 7:08 pm"
  }, {
    "postId" : "590554",
    "author" : {
      "username" : "jezek",
      "userId" : "590554",
      "joined" : "Fri Dec 03, 2004 11:28 pm",
      "profileRank" : "SSVC Member",
      "location" : "Logo Bus City",
      "postCount" : "875",
      "avatarPath" : "./download/file.php%3Favatar=1110_1291805311.jpg"
    },
    "content" : "i'll pop round and have alook , but busy until i come back from ebi4",
    "lastEdited" : "Thu Jun 09, 2011 6:45 am"
  }, {
    "postId" : "590564",
    "author" : {
      "username" : "Sancho",
      "userId" : "590564",
      "joined" : "Sat Jan 14, 2006 12:39 pm",
      "profileRank" : "Registered user",
      "location" : "Mechelen (Belgium)",
      "postCount" : "236",
      "avatarPath" : null
    },
    "content" : "<blockquote>\n <div>\n  <cite>jezek wrote:</cite>i'll pop round and have alook , but busy until i come back from ebi4\n </div>\n</blockquote>\n<br>\n<br>thxs a lot!",
    "lastEdited" : "Thu Jun 09, 2011 7:57 am"
  }, {
    "postId" : "591975",
    "author" : {
      "username" : "Grant Draper",
      "userId" : "591975",
      "joined" : "Tue May 26, 2009 6:34 pm",
      "profileRank" : "SSVC Member",
      "location" : "Derbyshire",
      "postCount" : "689",
      "avatarPath" : "./download/file.php%3Favatar=33163_1271432047.jpg"
    },
    "content" : "have a chat with this club, should get help from them.\n<br>\n<br> \n<!-- l -->\n<a class=\"postlink-local\" href=\"http://www.ssvc.org.uk/phpbb/viewtopic.php?f=10&amp;t=72202\">viewtopic.php?f=10&amp;t=72202</a>\n<!-- l -->\n<br>\n<br> \n<img class=\"smilies\" src=\"./images/smilies/icon_biggrin.gif\" alt=\":D\" title=\"Big Grin\">",
    "lastEdited" : "Thu Jun 16, 2011 7:33 am"
  } ]
}